.DS_Store
BinaryLens/BinaryLens.py
BinaryLens/__init__.py
BinaryLens-0.0.1.dist-info/LICENSE
BinaryLens-0.0.1.dist-info/METADATA
BinaryLens-0.0.1.dist-info/WHEEL
BinaryLens-0.0.1.dist-info/top_level.txt
BinaryLens-0.0.1.dist-info/RECORD
