Metadata-Version: 2.1
Name: BinaryLens
Version: 0.0.1
Summary: Gravitational Lensing by Binary Star
Home-page: https://github.com/tt-nakamura/GLBS
Author: Takahiro Nakamura
Author-email: a41757@gmail.com
License: UNKNOWN
Project-URL: Bug Tracker, https://github.com/tt-nakamura/GLBS/issues
Platform: UNKNOWN
Classifier: Programming Language :: Python :: 3
Classifier: License :: OSI Approved :: MIT License
Classifier: Operating System :: OS Independent
Requires-Python: >=3.6
License-File: LICENSE
